pyivp.cpython-38-x86_64-linux-gnu.so
pyivp-0.0.6.dist-info/LICENSE
pyivp-0.0.6.dist-info/METADATA
pyivp-0.0.6.dist-info/WHEEL
pyivp-0.0.6.dist-info/top_level.txt
pyivp-0.0.6.dist-info/RECORD
