Metadata-Version: 2.1
Name: pyivp
Version: 0.0.6
Summary: pyivp module
Home-page: https://github.com/ARG-NCTU/pyivp.git
Author: ARG
License-File: LICENSE
